[
	{
		"xfruitId":"G001",
		"title":"琯溪白玉蜜柚",
		"total":28,
		"pageCount":10,
		"big":"2个",
		"small":"1个",
		"price":"￥49.90/2个",
		"bigPriceAll":"￥49.90",
		"smallPriceAll":"￥39.90",
		"bigPrice":"49.90",
		"smallPrice":"39.90",
		"imgurl":"css/img/content1.jpg",
		"imgurlContentList":"../css/img/content1.jpg",
		"imgurlList":"../css/img/list1.jpg",
		"imgurlCollection":["../css/img/G001_1.jpg","../css/img/G001_2.jpg","../css/img/G001_3.jpg","../css/img/G001_4.jpg","../css/img/G001_5.jpg","../css/img/G001_6.jpg","../css/img/G001_7.jpg","../css/img/G001_8.jpg"],
		"condition":"新品",
		"intro":"柚惑热情  洋溢水润的甜",
		"data":[	{"../css/img/personImgurl":"../css/img/person1.jpg","star":"4","comment":"很有水分，分量很足，满甜的，不错，就是略贵","time":"2016-10-12 08:23:12"},
					{"../css/img/personImgurl":"../css/img/person2.jpg","star":"4","comment":"比较酸，皮厚，肉比较硬啊","time":"2016-10-10 11:36:43"},
					{"../css/img/personImgurl":"../css/img/person3.jpg","star":"3","comment":"甜，水份多","time":"2016-10-09 13:23:14"},
					{"../css/img/personImgurl":"../css/img/person4.jpg","star":"5","comment":"挺新鲜的，甜度尚可","time":"2016-10-08 15:46:12"},
					{"../css/img/personImgurl":"../css/img/person5.jpg","star":"3","comment":"还行。就是价格有点小高。","time":"2016-10-08 12:23:22"},
					{"../css/img/personImgurl":"../css/img/person6.jpg","star":"5","comment":"第二次买了，真心不错","time":"2016-10-07 14:46:12"},
					{"../css/img/personImgurl":"../css/img/person7.jpg","star":"4","comment":"比较酸，皮厚，肉比较硬啊","time":"2016-10-05 15:46:55"},
					{"../css/img/personImgurl":"../css/img/person8.jpg","star":"3","comment":"果果不错，第一次吃很满意","time":"2016-10-04 13:32:16"},
					{"../css/img/personImgurl":"../css/img/person9.jpg","star":"4","comment":"外表看着还行，里面偏干，水分不是很足。","time":"2016-10-01 14:52:52"},
					{"../css/img/personImgurl":"../css/img/person9.jpg","star":"5","comment":"非常好吃 一直都来","time":"2016-09-21 12:32:22"},
					{"../css/img/personImgurl":"../css/img/person11.jpg","star":"3","comment":"水分有点少，甜度有","time":"2016-09-20 08:23:55"},
					{"../css/img/personImgurl":"../css/img/person12.jpg","star":"2","comment":"实在没有买过这样的柚子，花了几倍的价格买回来一堆皮，给一颗星都多了，绝对的差评！","time":"2016-09-18 08:32:45"},
					{"../css/img/personImgurl":"../css/img/person13.jpg","star":"5","comment":"实体店买了一个红柚有点苦，可是这个柚子就是甜的，而且水分比较足，很赞","time":"2016-09-16 13:32:55"},
					{"../css/img/personImgurl":"../css/img/person14.jpg","star":"3","comment":"不太满意，今年第一次在天天果园买柚子，价格不便宜，但是打开第一个皮厚到飞起，果肉大小跟文旦差不多，也是醉醉的，还是去水果店自己挑比较靠谱","time":"2016-09-14 08:46:21"},
					{"../css/img/personImgurl":"../css/img/person15.jpg","star":"4","comment":"我这次买了4个不怎么样","time":"2016-08-13 12:23:15"},
					{"../css/img/personImgurl":"../css/img/person16.jpg","star":"5","comment":"口感不错。好吃","time":"2016-08-12 18:46:55"},
					{"../css/img/personImgurl":"../css/img/person17.jpg","star":"4","comment":"柚子很甜，水分很充足","time":"2016-06-11 02:46:51"},
					{"../css/img/personImgurl":"../css/img/person18.jpg","star":"3","comment":"果皮厚度正常水平，果肉红润，未见\"三红\"，口味上略呈酸味，甜度不高，含水量一般，综上，小贵。","time":"2016-04-06 17:23:51"},
					{"../css/img/personImgurl":"../css/img/person19.jpg","star":"5","comment":"看起来棒棒哒","time":"2016-03-02 02:23:35"},
					{"../css/img/personImgurl":"../css/img/person20.jpg","star":"4","comment":"味道还可以，稍微有些干","time":"2016-02-14 15:46:25"},
					{"../css/img/personImgurl":"../css/img/person21.jpg","star":"4","comment":"这次比上次的好 水分比较多 每一瓣蛮大的 上次的就比较小 就是水分多了不怎么甜","time":"2016-02-10 12:32:55"},
					{"../css/img/personImgurl":"../css/img/person22.jpg","star":"5","comment":"快递小哥很给力","time":"2016-01-12 15:32:45"},
					{"../css/img/personImgurl":"../css/img/person23.jpg","star":"4","comment":"好吃，唯一缺点就是皮太厚咯","time":"2016-01-05 15:23:13"},
					{"../css/img/personImgurl":"../css/img/person24.jpg","star":"3","comment":"很甜，很不错，下次再买！","time":"2016-01-04 12:46:55"},
					{"../css/img/personImgurl":"../css/img/person26.jpg","star":"6","comment":"个头不大，皮超级厚，有点酸，真心不咋地还贵","time":"2015-12-18 08:23:21"},
					{"../css/img/personImgurl":"../css/img/person26.jpg","star":"4","comment":"偏酸喜欢的可以下手了水分很好","time":"2015-10-22 12:32:12"},
					{"../css/img/personImgurl":"../css/img/person27.jpg","star":"4","comment":"不知道这个为什么那么贵，实际就是这样的，皮那么厚，肉也没有那么多汁肥嫩。下次不会买了","time":"2015-07-12 08:32:56"},
					{"../css/img/personImgurl":"../css/img/person28.jpg","star":"4","comment":"起码样子长得挺好看的","time":"2015-07-05 03:12:12"}
				]
	},
	{
		"xfruitId":"G002",
		"title":"美国有籽红提",
		"total":16,
		"pageCount":10,
		"big":"2斤",
		"small":"1斤",
		"price":"￥58.00/2斤",
		"bigPriceAll":"￥58.00",
		"smallPriceAll":"￥32.00",
		"bigPrice":"58.00",
		"smallPrice":"32.00",
		"imgurl":"css/img/content2.jpg",
		"imgurlContentList":"../css/img/content2.jpg",
		"imgurlList":"../css/img/list2.jpg",
		"imgurlCollection":["../css/img/G002_1.jpg","../css/img/G002_2.jpg","../css/img/G002_3.jpg","../css/img/G002_4.jpg","../css/img/G002_5.jpg","../css/img/G002_6.jpg","../css/img/G002_7.jpg","../css/img/G002_8.jpg"],
		"condition":"补货中",
		"intro":"果肉甜沁  点亮味蕾",
		"data":[	
					{"../css/img/personImgurl":"../css/img/person3.jpg","star":"3","comment":"甜，水份多","time":"2016-10-09 13:23:14"},
					{"../css/img/personImgurl":"../css/img/person5.jpg","star":"3","comment":"还行。就是价格有点小高。","time":"2016-10-08 12:23:22"},
					{"../css/img/personImgurl":"../css/img/person6.jpg","star":"5","comment":"第二次买了，真心不错","time":"2016-10-07 14:46:12"},
					{"../css/img/personImgurl":"../css/img/person7.jpg","star":"4","comment":"比较酸，皮厚，肉比较硬啊","time":"2016-10-05 15:46:55"},
					{"../css/img/personImgurl":"../css/img/person16.jpg","star":"5","comment":"口感不错。好吃","time":"2016-08-12 18:46:55"},
					{"../css/img/personImgurl":"../css/img/person17.jpg","star":"4","comment":"柚子很甜，水分很充足","time":"2016-06-11 02:46:51"},
					{"../css/img/personImgurl":"../css/img/person18.jpg","star":"3","comment":"果皮厚度正常水平，果肉红润，未见\"三红\"，口味上略呈酸味，甜度不高，含水量一般，综上，小贵。","time":"2016-04-06 17:23:51"},
					{"../css/img/personImgurl":"../css/img/person19.jpg","star":"5","comment":"看起来棒棒哒","time":"2016-03-02 02:23:35"},
					{"../css/img/personImgurl":"../css/img/person20.jpg","star":"4","comment":"味道还可以，稍微有些干","time":"2016-02-14 15:46:25"},
					{"../css/img/personImgurl":"../css/img/person21.jpg","star":"4","comment":"这次比上次的好 水分比较多 每一瓣蛮大的 上次的就比较小 就是水分多了不怎么甜","time":"2016-02-10 12:32:55"},
					{"../css/img/personImgurl":"../css/img/person23.jpg","star":"4","comment":"好吃，唯一缺点就是皮太厚咯","time":"2016-01-05 15:23:13"},
					{"../css/img/personImgurl":"../css/img/person24.jpg","star":"3","comment":"很甜，很不错，下次再买！","time":"2016-01-04 12:46:55"},
					{"../css/img/personImgurl":"../css/img/person16.jpg","star":"6","comment":"个头不大，皮超级厚，有点酸，真心不咋地还贵","time":"2015-12-18 08:23:21"},
					{"../css/img/personImgurl":"../css/img/person26.jpg","star":"4","comment":"偏酸喜欢的可以下手了水分很好","time":"2015-10-22 12:32:12"},
					{"../css/img/personImgurl":"../css/img/person27.jpg","star":"4","comment":"不知道这个为什么那么贵，实际就是这样的，皮那么厚，肉也没有那么多汁肥嫩。下次不会买了","time":"2015-07-12 08:32:56"},
					{"../css/img/personImgurl":"../css/img/person28.jpg","star":"4","comment":"起码样子长得挺好看的","time":"2015-07-05 03:12:12"}
				]
	},
	{
		"xfruitId":"G003",
		"title":"丽江雪桃",
		"total":24,
		"pageCount":10,
		"big":"3个",
		"small":"1个",
		"total":18,
		"pageCount":10,
		"price":"￥88.00/3个",
		"bigPriceAll":"￥88.00",
		"smallPriceAll":"￥38.00",
		"bigPrice":"88.00",
		"smallPrice":"38.00",
		"imgurl":"css/img/content3.jpg",
		"imgurlContentList":"../css/img/content3.jpg",
		"imgurlList":"../css/img/list3.jpg",
		"imgurlCollection":["../css/img/G003_1.jpg","../css/img/G003_2.jpg","../css/img/G003_3.jpg","../css/img/G003_4.jpg","../css/img/G003_5.jpg","../css/img/G003_6.jpg","../css/img/G003_7.jpg","../css/img/G003_8.jpg"],
		"condition":"新品",
		"intro":"200天的等待，堪比蟠桃来",
		"data":[	
					{"../css/img/personImgurl":"../css/img/person2.jpg","star":"4","comment":"很有水分，分量很足，满甜的，不错，就是略贵","time":"2016-10-10 11:36:43"},
					{"../css/img/personImgurl":"../css/img/person3.jpg","star":"3","comment":"甜，水份多","time":"2016-10-09 13:23:14"},
					{"../css/img/personImgurl":"../css/img/person5.jpg","star":"3","comment":"还行。就是价格有点小高。","time":"2016-10-08 12:23:22"},
					{"../css/img/personImgurl":"../css/img/person6.jpg","star":"5","comment":"第二次买了，真心不错","time":"2016-10-07 14:46:12"},
					{"../css/img/personImgurl":"../css/img/person7.jpg","star":"4","comment":"比较酸，皮厚，肉比较硬啊","time":"2016-10-05 15:46:55"},
					{"../css/img/personImgurl":"../css/img/person8.jpg","star":"3","comment":"果果不错，第一次吃很满意","time":"2016-10-04 13:32:16"},
					{"../css/img/personImgurl":"../css/img/person9.jpg","star":"4","comment":"外表看着还行，里面偏干，水分不是很足。","time":"2016-10-01 14:52:52"},
					{"../css/img/personImgurl":"../css/img/person9.jpg","star":"5","comment":"非常好吃 一直都来","time":"2016-09-21 12:32:22"},
					{"../css/img/personImgurl":"../css/img/person11.jpg","star":"3","comment":"水分有点少，甜度有","time":"2016-09-20 08:23:55"},
					{"../css/img/personImgurl":"../css/img/person13.jpg","star":"5","comment":"实体店买了一个红柚有点苦，可是这个柚子就是甜的，而且水分比较足，很赞","time":"2016-09-16 13:32:55"},
					{"../css/img/personImgurl":"../css/img/person14.jpg","star":"3","comment":"不太满意，今年第一次在天天果园买柚子，价格不便宜，但是打开第一个皮厚到飞起，果肉大小跟文旦差不多，也是醉醉的，还是去水果店自己挑比较靠谱","time":"2016-09-14 08:46:21"},
					{"../css/img/personImgurl":"../css/img/person15.jpg","star":"4","comment":"我这次买了4个不怎么样","time":"2016-08-13 12:23:15"},
					{"../css/img/personImgurl":"../css/img/person16.jpg","star":"5","comment":"口感不错。好吃","time":"2016-08-12 18:46:55"},
					{"../css/img/personImgurl":"../css/img/person18.jpg","star":"3","comment":"果皮厚度正常水平，果肉红润，未见\"三红\"，口味上略呈酸味，甜度不高，含水量一般，综上，小贵。","time":"2016-04-06 17:23:51"},
					{"../css/img/personImgurl":"../css/img/person19.jpg","star":"5","comment":"看起来棒棒哒","time":"2016-03-02 02:23:35"},
					{"../css/img/personImgurl":"../css/img/person20.jpg","star":"4","comment":"味道还可以，稍微有些干","time":"2016-02-14 15:46:25"},
					{"../css/img/personImgurl":"../css/img/person21.jpg","star":"4","comment":"这次比上次的好 水分比较多 每一瓣蛮大的 上次的就比较小 就是水分多了不怎么甜","time":"2016-02-10 12:32:55"},
					{"../css/img/personImgurl":"../css/img/person22.jpg","star":"5","comment":"快递小哥很给力","time":"2016-01-12 15:32:45"},
					{"../css/img/personImgurl":"../css/img/person23.jpg","star":"4","comment":"好吃，唯一缺点就是皮太厚咯","time":"2016-01-05 15:23:13"},
					{"../css/img/personImgurl":"../css/img/person24.jpg","star":"3","comment":"很甜，很不错，下次再买！","time":"2016-01-04 12:46:55"},
					{"../css/img/personImgurl":"../css/img/person26.jpg","star":"6","comment":"个头不大，皮超级厚，有点酸，真心不咋地还贵","time":"2015-12-18 08:23:21"},
					{"../css/img/personImgurl":"../css/img/person6.jpg","star":"4","comment":"偏酸喜欢的可以下手了水分很好","time":"2015-10-22 12:32:12"},
					{"../css/img/personImgurl":"../css/img/person27.jpg","star":"4","comment":"不知道这个为什么那么贵，实际就是这样的，皮那么厚，肉也没有那么多汁肥嫩。下次不会买了","time":"2015-07-12 08:32:56"},
					{"../css/img/personImgurl":"../css/img/person28.jpg","star":"4","comment":"起码样子长得挺好看的","time":"2015-07-05 03:12:12"}
				]
		
	},
	{
		"xfruitId":"G004",
		"title":"云南蒙自石榴",
		"total":28,
		"pageCount":10,
		"big":"6+2个",
		"small":"2个",
		"price":"￥39.90/6+2个",
		"bigPriceAll":"￥39.90",
		"smallPriceAll":"￥15.00",
		"bigPrice":"39.90",
		"smallPrice":"15.00",
		"imgurl":"css/img/content4.jpg",
		"imgurlContentList":"../css/img/content4.jpg",
		"imgurlList":"../css/img/list4.jpg",
		"imgurlCollection":["../css/img/G004_1.jpg","../css/img/G004_2.jpg","../css/img/G004_3.jpg","../css/img/G004_4.jpg","../css/img/G004_5.jpg","../css/img/G004_6.jpg","../css/img/G004_7.jpg","../css/img/G004_8.jpg"],
		"condition":"买6个送2个",
		"intro":"满满的粉色世界  口口的清甜水嫩",
		"data":[	{"../css/img/personImgurl":"../css/img/person15.jpg","star":"4","comment":"满满的粉色世界  口口的清甜水嫩","time":"2016-10-12 08:23:12"},
					{"../css/img/personImgurl":"../css/img/person25.jpg","star":"4","comment":"很有水分，分量很足，满甜的，不错，就是略贵","time":"2016-10-10 11:36:43"},
					{"../css/img/personImgurl":"../css/img/person23.jpg","star":"3","comment":"甜，水份多","time":"2016-10-09 13:23:14"},
					{"../css/img/personImgurl":"../css/img/person4.jpg","star":"5","comment":"挺新鲜的，甜度尚可","time":"2016-10-08 15:46:12"},
					{"../css/img/personImgurl":"../css/img/person15.jpg","star":"3","comment":"还行。就是价格有点小高。","time":"2016-10-08 12:23:22"},
					{"../css/img/personImgurl":"../css/img/person26.jpg","star":"5","comment":"第二次买了，真心不错","time":"2016-10-07 14:46:12"},
					{"../css/img/personImgurl":"../css/img/person7.jpg","star":"4","comment":"比较酸，皮厚，肉比较硬啊","time":"2016-10-05 15:46:55"},
					{"../css/img/personImgurl":"../css/img/person18.jpg","star":"3","comment":"果果不错，第一次吃很满意","time":"2016-10-04 13:32:16"},
					{"../css/img/personImgurl":"../css/img/person9.jpg","star":"4","comment":"外表看着还行，里面偏干，水分不是很足。","time":"2016-10-01 14:52:52"},
					{"../css/img/personImgurl":"../css/img/person9.jpg","star":"5","comment":"非常好吃 一直都来","time":"2016-09-21 12:32:22"},
					{"../css/img/personImgurl":"../css/img/person1.jpg","star":"3","comment":"水分有点少，甜度有","time":"2016-09-20 08:23:55"},
					{"../css/img/personImgurl":"../css/img/person12.jpg","star":"2","comment":"实在没有买过这样的柚子，花了几倍的价格买回来一堆皮，给一颗星都多了，绝对的差评！","time":"2016-09-18 08:32:45"},
					{"../css/img/personImgurl":"../css/img/person3.jpg","star":"5","comment":"实体店买了一个红柚有点苦，可是这个柚子就是甜的，而且水分比较足，很赞","time":"2016-09-16 13:32:55"},
					{"../css/img/personImgurl":"../css/img/person14.jpg","star":"3","comment":"不太满意，今年第一次在天天果园买柚子，价格不便宜，但是打开第一个皮厚到飞起，果肉大小跟文旦差不多，也是醉醉的，还是去水果店自己挑比较靠谱","time":"2016-09-14 08:46:21"},
					{"../css/img/personImgurl":"../css/img/person15.jpg","star":"4","comment":"我这次买了4个不怎么样","time":"2016-08-13 12:23:15"},
					{"../css/img/personImgurl":"../css/img/person6.jpg","star":"5","comment":"口感不错。好吃","time":"2016-08-12 18:46:55"},
					{"../css/img/personImgurl":"../css/img/person17.jpg","star":"4","comment":"柚子很甜，水分很充足","time":"2016-06-11 02:46:51"},
					{"../css/img/personImgurl":"../css/img/person18.jpg","star":"3","comment":"果皮厚度正常水平，果肉红润，未见\"三红\"，口味上略呈酸味，甜度不高，含水量一般，综上，小贵。","time":"2016-04-06 17:23:51"},
					{"../css/img/personImgurl":"../css/img/person19.jpg","star":"5","comment":"看起来棒棒哒","time":"2016-03-02 02:23:35"},
					{"../css/img/personImgurl":"../css/img/person20.jpg","star":"4","comment":"味道还可以，稍微有些干","time":"2016-02-14 15:46:25"},
					{"../css/img/personImgurl":"../css/img/person21.jpg","star":"4","comment":"这次比上次的好 水分比较多 每一瓣蛮大的 上次的就比较小 就是水分多了不怎么甜","time":"2016-02-10 12:32:55"},
					{"../css/img/personImgurl":"../css/img/person22.jpg","star":"5","comment":"快递小哥很给力","time":"2016-01-12 15:32:45"},
					{"../css/img/personImgurl":"../css/img/person23.jpg","star":"4","comment":"好吃，唯一缺点就是皮太厚咯","time":"2016-01-05 15:23:13"},
					{"../css/img/personImgurl":"../css/img/person24.jpg","star":"3","comment":"很甜，很不错，下次再买！","time":"2016-01-04 12:46:55"},
					{"../css/img/personImgurl":"../css/img/person16.jpg","star":"6","comment":"个头不大，皮超级厚，有点酸，真心不咋地还贵","time":"2015-12-18 08:23:21"},
					{"../css/img/personImgurl":"../css/img/person26.jpg","star":"4","comment":"偏酸喜欢的可以下手了水分很好","time":"2015-10-22 12:32:12"},
					{"../css/img/personImgurl":"../css/img/person27.jpg","star":"4","comment":"不知道这个为什么那么贵，实际就是这样的，皮那么厚，肉也没有那么多汁肥嫩。下次不会买了","time":"2015-07-12 08:32:56"},
					{"../css/img/personImgurl":"../css/img/person28.jpg","star":"4","comment":"起码样子长得挺好看的","time":"2015-07-05 03:12:12"}
				]
	},
	{
		"xfruitId":"G005",
		"title":"奇异小莓",
		"small":"2盒",
		"total":13,
		"pageCount":10,
		"price":"￥49.00/2盒",
		"smallPriceAll":"￥49.00",
		"smallPrice":"49.00",
		"imgurl":"css/img/content5.jpg",
		"imgurlContentList":"../css/img/content5.jpg",
		"imgurlList":"../css/img/list5.jpg",
		"imgurlCollection":["../css/img/G005_1.jpg","../css/img/G005_2.jpg","../css/img/G005_3.jpg","../css/img/G005_4.jpg","../css/img/G005_5.jpg","../css/img/G005_6.jpg","../css/img/G005_7.jpg","../css/img/G005_8.jpg"],
		"condition":"新品",
		"intro":"迷你小不点   一口一个糯糯的",
		"data":[	{"../css/img/personImgurl":"../css/img/person11.jpg","star":"4","comment":"很有水分，分量很足，满甜的，不错，就是略贵","time":"2016-10-12 08:23:12"},
					{"../css/img/personImgurl":"../css/img/person24.jpg","star":"5","comment":"挺新鲜的，甜度尚可","time":"2016-10-08 15:46:12"},
					{"../css/img/personImgurl":"../css/img/person5.jpg","star":"3","comment":"还行。就是价格有点小高。","time":"2016-10-08 12:23:22"},
					{"../css/img/personImgurl":"../css/img/person7.jpg","star":"4","comment":"比较酸，皮厚，肉比较硬啊","time":"2016-10-05 15:46:55"},
					{"../css/img/personImgurl":"../css/img/person8.jpg","star":"3","comment":"果果不错，第一次吃很满意","time":"2016-10-04 13:32:16"},
					{"../css/img/personImgurl":"../css/img/person9.jpg","star":"4","comment":"外表看着还行，里面偏干，水分不是很足。","time":"2016-10-01 14:52:52"},
					{"../css/img/personImgurl":"../css/img/person19.jpg","star":"5","comment":"非常好吃 一直都来","time":"2016-09-21 12:32:22"},
					{"../css/img/personImgurl":"../css/img/person13.jpg","star":"3","comment":"水分有点少，甜度有","time":"2016-09-20 08:23:55"},
					{"../css/img/personImgurl":"../css/img/person2.jpg","star":"2","comment":"实在没有买过这样的柚子，花了几倍的价格买回来一堆皮，给一颗星都多了，绝对的差评！","time":"2016-09-18 08:32:45"},
					{"../css/img/personImgurl":"../css/img/person1.jpg","star":"5","comment":"实体店买了一个红柚有点苦，可是这个柚子就是甜的，而且水分比较足，很赞","time":"2016-09-16 13:32:55"},
					{"../css/img/personImgurl":"../css/img/person14.jpg","star":"3","comment":"不太满意，今年第一次在天天果园买柚子，价格不便宜，但是打开第一个皮厚到飞起，果肉大小跟文旦差不多，也是醉醉的，还是去水果店自己挑比较靠谱","time":"2016-09-14 08:46:21"},
					{"../css/img/personImgurl":"../css/img/person18.jpg","star":"3","comment":"果皮厚度正常水平，果肉红润，未见\"三红\"，口味上略呈酸味，甜度不高，含水量一般，综上，小贵。","time":"2016-04-06 17:23:51"},
					{"../css/img/personImgurl":"../css/img/person28.jpg","star":"4","comment":"起码样子长得挺好看的","time":"2015-07-05 03:12:12"}
				]
	},
	{
		"xfruitId":"G006",
		"title":"新疆库尔勒香梨",
		"total":20,
		"pageCount":10,
		"small":"2斤",
		"price":"￥29.90/2斤",
		"smallPriceAll":"￥29.90",
		"smallPrice":"29.90",
		"imgurl":"css/img/content6.jpg",
		"imgurlContentList":"../css/img/content6.jpg",
		"imgurlList":"../css/img/list6.jpg",
		"imgurlCollection":["../css/img/G006_1.jpg","../css/img/G006_2.jpg","../css/img/G006_3.jpg","../css/img/G006_4.jpg","../css/img/G006_5.jpg","../css/img/G006_6.jpg","../css/img/G006_7.jpg","../css/img/G006_8.jpg"],
		"condition":"新品",
		"intro":"经久不褪的清脆动人",
		"data":[	
					{"../css/img/personImgurl":"../css/img/person2.jpg","star":"4","comment":"很有水分，分量很足，满甜的，不错，就是略贵","time":"2016-10-10 11:36:43"},
					{"../css/img/personImgurl":"../css/img/person5.jpg","star":"3","comment":"还行。就是价格有点小高。","time":"2016-10-08 12:23:22"},
					{"../css/img/personImgurl":"../css/img/person6.jpg","star":"5","comment":"第二次买了，真心不错","time":"2016-10-07 14:46:12"},
					{"../css/img/personImgurl":"../css/img/person8.jpg","star":"3","comment":"果果不错，第一次吃很满意","time":"2016-10-04 13:32:16"},
					{"../css/img/personImgurl":"../css/img/person9.jpg","star":"5","comment":"非常好吃 一直都来","time":"2016-09-21 12:32:22"},
					{"../css/img/personImgurl":"../css/img/person11.jpg","star":"3","comment":"水分有点少，甜度有","time":"2016-09-20 08:23:55"},
					{"../css/img/personImgurl":"../css/img/person13.jpg","star":"5","comment":"实体店买了一个红柚有点苦，可是这个柚子就是甜的，而且水分比较足，很赞","time":"2016-09-16 13:32:55"},
					{"../css/img/personImgurl":"../css/img/person14.jpg","star":"3","comment":"不太满意，今年第一次在天天果园买柚子，价格不便宜，但是打开第一个皮厚到飞起，果肉大小跟文旦差不多，也是醉醉的，还是去水果店自己挑比较靠谱","time":"2016-09-14 08:46:21"},
					{"../css/img/personImgurl":"../css/img/person15.jpg","star":"4","comment":"我这次买了4个不怎么样","time":"2016-08-13 12:23:15"},
					{"../css/img/personImgurl":"../css/img/person18.jpg","star":"3","comment":"果皮厚度正常水平，果肉红润，未见\"三红\"，口味上略呈酸味，甜度不高，含水量一般，综上，小贵。","time":"2016-04-06 17:23:51"},
					{"../css/img/personImgurl":"../css/img/person19.jpg","star":"5","comment":"看起来棒棒哒","time":"2016-03-02 02:23:35"},
					{"../css/img/personImgurl":"../css/img/person20.jpg","star":"4","comment":"味道还可以，稍微有些干","time":"2016-02-14 15:46:25"},
					{"../css/img/personImgurl":"../css/img/person21.jpg","star":"4","comment":"这次比上次的好 水分比较多 每一瓣蛮大的 上次的就比较小 就是水分多了不怎么甜","time":"2016-02-10 12:32:55"},
					{"../css/img/personImgurl":"../css/img/person22.jpg","star":"5","comment":"快递小哥很给力","time":"2016-01-12 15:32:45"},
					{"../css/img/personImgurl":"../css/img/person23.jpg","star":"4","comment":"好吃，唯一缺点就是皮太厚咯","time":"2016-01-05 15:23:13"},
					{"../css/img/personImgurl":"../css/img/person24.jpg","star":"3","comment":"很甜，很不错，下次再买！","time":"2016-01-04 12:46:55"},
					{"../css/img/personImgurl":"../css/img/person26.jpg","star":"6","comment":"个头不大，皮超级厚，有点酸，真心不咋地还贵","time":"2015-12-18 08:23:21"},
					{"../css/img/personImgurl":"../css/img/person6.jpg","star":"4","comment":"偏酸喜欢的可以下手了水分很好","time":"2015-10-22 12:32:12"},
					{"../css/img/personImgurl":"../css/img/person27.jpg","star":"4","comment":"不知道这个为什么那么贵，实际就是这样的，皮那么厚，肉也没有那么多汁肥嫩。下次不会买了","time":"2015-07-12 08:32:56"},
					{"../css/img/personImgurl":"../css/img/person28.jpg","star":"4","comment":"起码样子长得挺好看的","time":"2015-07-05 03:12:12"}
				]
	},
	{
		"xfruitId":"G007",
		"title":"澳大利亚蜜桔",
		"big":"6个",
		"small":"3个",
		"total":15,
		"pageCount":10,
		"price":"￥49.90/6个",
		"bigPriceAll":"￥49.90",
		"smallPriceAll":"￥28.00",
		"bigPrice":"49.90",
		"smallPrice":"28.00",
		"imgurl":"css/img/content7.jpg",
		"imgurlContentList":"../css/img/content7.jpg",
		"imgurlList":"../css/img/list7.jpg",
		"imgurlCollection":["../css/img/G007_1.jpg","../css/img/G007_2.jpg","../css/img/G007_3.jpg","../css/img/G007_4.jpg","../css/img/G007_5.jpg","../css/img/G007_6.jpg"],
		"condition":"",
		"intro":"瓣瓣果肉  丝丝水润",
		"data":[	
					{"../css/img/personImgurl":"../css/img/person25.jpg","star":"4","comment":"很有水分，分量很足，满甜的，不错，就是略贵","time":"2016-10-12 08:23:12"},
					{"../css/img/personImgurl":"../css/img/person22.jpg","star":"4","comment":"比较酸，皮厚，肉比较硬啊","time":"2016-10-10 11:36:43"},
					{"../css/img/personImgurl":"../css/img/person23.jpg","star":"3","comment":"甜，水份多","time":"2016-10-09 13:23:14"},
					{"../css/img/personImgurl":"../css/img/person24.jpg","star":"5","comment":"挺新鲜的，甜度尚可","time":"2016-10-08 15:46:12"},
					{"../css/img/personImgurl":"../css/img/person10.jpg","star":"3","comment":"还行。就是价格有点小高。","time":"2016-10-08 12:23:22"},
					{"../css/img/personImgurl":"../css/img/person7.jpg","star":"4","comment":"比较酸，皮厚，肉比较硬啊","time":"2016-10-05 15:46:55"},
					{"../css/img/personImgurl":"../css/img/person16.jpg","star":"5","comment":"口感不错。好吃","time":"2016-08-12 18:46:55"},
					{"../css/img/personImgurl":"../css/img/person19.jpg","star":"5","comment":"看起来棒棒哒","time":"2016-03-02 02:23:35"},
					{"../css/img/personImgurl":"../css/img/person20.jpg","star":"4","comment":"味道还可以，稍微有些干","time":"2016-02-14 15:46:25"},
					{"../css/img/personImgurl":"../css/img/person2.jpg","star":"4","comment":"这次比上次的好 水分比较多 每一瓣蛮大的 上次的就比较小 就是水分多了不怎么甜","time":"2016-02-10 12:32:55"},
					{"../css/img/personImgurl":"../css/img/person5.jpg","star":"5","comment":"快递小哥很给力","time":"2016-01-12 15:32:45"},
					{"../css/img/personImgurl":"../css/img/person3.jpg","star":"4","comment":"好吃，唯一缺点就是皮太厚咯","time":"2016-01-05 15:23:13"},
					{"../css/img/personImgurl":"../css/img/person4.jpg","star":"3","comment":"很甜，很不错，下次再买！","time":"2016-01-04 12:46:55"},
					{"../css/img/personImgurl":"../css/img/person1.jpg","star":"6","comment":"个头不大，皮超级厚，有点酸，真心不咋地还贵","time":"2015-12-18 08:23:21"},
					{"../css/img/personImgurl":"../css/img/person26.jpg","star":"4","comment":"偏酸喜欢的可以下手了水分很好","time":"2015-10-22 12:32:12"}
				]
	},
	{
		"xfruitId":"G008",
		"title":"泰国山竹",
		"total":10,
		"pageCount":10,
		"big":"2斤",
		"small":"1斤",
		"price":"￥58.00/2斤",
		"bigPriceAll":"￥58.00",
		"smallPriceAll":"￥36.00",
		"bigPrice":"58.00",
		"smallPrice":"36.00",
		"imgurl":"css/img/content8.jpg",
		"imgurlContentList":"../css/img/content8.jpg",
		"imgurlList":"../css/img/list8.jpg",
		"imgurlCollection":["../css/img/G008_1.jpg","../css/img/G008_2.jpg","../css/img/G008_3.jpg","../css/img/G008_4.jpg","../css/img/G008_5.jpg","../css/img/G008_6.jpg"],
		"condition":"",
		"intro":"清新淡雅  沁心爽甜",
		"data":[	
					{"../css/img/personImgurl":"../css/img/person5.jpg","star":"3","comment":"还行。就是价格有点小高。","time":"2016-10-08 12:23:22"},
					{"../css/img/personImgurl":"../css/img/person6.jpg","star":"5","comment":"第二次买了，真心不错","time":"2016-10-07 14:46:12"},
					{"../css/img/personImgurl":"../css/img/person7.jpg","star":"4","comment":"比较酸，皮厚，肉比较硬啊","time":"2016-10-05 15:46:55"},
					{"../css/img/personImgurl":"../css/img/person8.jpg","star":"3","comment":"果果不错，第一次吃很满意","time":"2016-10-04 13:32:16"},
					{"../css/img/personImgurl":"../css/img/person2.jpg","star":"2","comment":"实在没有买过这样的柚子，花了几倍的价格买回来一堆皮，给一颗星都多了，绝对的差评！","time":"2016-09-18 08:32:45"},
					{"../css/img/personImgurl":"../css/img/person1.jpg","star":"5","comment":"实体店买了一个红柚有点苦，可是这个柚子就是甜的，而且水分比较足，很赞","time":"2016-09-16 13:32:55"},
					{"../css/img/personImgurl":"../css/img/person19.jpg","star":"5","comment":"看起来棒棒哒","time":"2016-03-02 02:23:35"},
					{"../css/img/personImgurl":"../css/img/person26.jpg","star":"6","comment":"个头不大，皮超级厚，有点酸，真心不咋地还贵","time":"2015-12-18 08:23:21"},
					{"../css/img/personImgurl":"../css/img/person27.jpg","star":"4","comment":"不知道这个为什么那么贵，实际就是这样的，皮那么厚，肉也没有那么多汁肥嫩。下次不会买了","time":"2015-07-12 08:32:56"},
					{"../css/img/personImgurl":"../css/img/person28.jpg","star":"4","comment":"起码样子长得挺好看的","time":"2015-07-05 03:12:12"}
				]
	},
	{
		"xfruitId":"G009",
		"title":"泰国椰青",
		"total":7,
		"pageCount":7,
		"big":"4个",
		"small":"2个",
		"price":"￥49.90/4个",
		"bigPriceAll":"￥49.90",
		"smallPriceAll":"￥31.00",
		"bigPrice":"49.90",
		"smallPrice":"31.00",
		"imgurl":"css/img/content9.jpg",
		"imgurlContentList":"../css/img/content9.jpg",
		"imgurlList":"../css/img/list9.jpg",
		"imgurlCollection":["../css/img/G009_1.jpg","../css/img/G009_2.jpg","../css/img/G009_3.jpg","../css/img/G009_4.jpg","../css/img/G009_5.jpg","../css/img/G009_6.jpg","../css/img/G009_7.jpg","../css/img/G009_8.jpg"],
		"condition":"包邮送开椰器",
		"intro":"天然果汁  浓郁椰香",
		"data":[	
					{"../css/img/personImgurl":"../css/img/person5.jpg","star":"3","comment":"还行。就是价格有点小高。","time":"2016-10-08 12:23:22"},
					{"../css/img/personImgurl":"../css/img/person6.jpg","star":"5","comment":"第二次买了，真心不错","time":"2016-10-07 14:46:12"},
					{"../css/img/personImgurl":"../css/img/person8.jpg","star":"3","comment":"果果不错，第一次吃很满意","time":"2016-10-04 13:32:16"},
					{"../css/img/personImgurl":"../css/img/person19.jpg","star":"5","comment":"看起来棒棒哒","time":"2016-03-02 02:23:35"},
					{"../css/img/personImgurl":"../css/img/person26.jpg","star":"6","comment":"个头不大，皮超级厚，有点酸，真心不咋地还贵","time":"2015-12-18 08:23:21"},
					{"../css/img/personImgurl":"../css/img/person27.jpg","star":"4","comment":"不知道这个为什么那么贵，实际就是这样的，皮那么厚，肉也没有那么多汁肥嫩。下次不会买了","time":"2015-07-12 08:32:56"},
					{"../css/img/personImgurl":"../css/img/person28.jpg","star":"4","comment":"起码样子长得挺好看的","time":"2015-07-05 03:12:12"}
				]
	},
	{
		"xfruitId":"G010",
		"title":"新西兰柠檬",
		"total":23,
		"pageCount":10,
		"big":"8个",
		"small":"4个",
		"price":"￥29.00/8个",
		"bigPriceAll":"￥29.00",
		"smallPriceAll":"￥16.00",
		"bigPrice":"29.00",
		"smallPrice":"16.00",
		"imgurl":"css/img/content10.jpg",
		"imgurlContentList":"../css/img/content10.jpg",
		"imgurlList":"../css/img/list10.jpg",
		"imgurlCollection":["../css/img/G010_1.jpg","../css/img/G010_2.jpg","../css/img/G010_3.jpg","../css/img/G010_4.jpg","../css/img/G010_5.jpg","../css/img/G010_6.jpg"],
		"condition":"新品",
		"intro":"鲜橙靓皮  柠香清新",
		"data":[	
					{"../css/img/personImgurl":"../css/img/person3.jpg","star":"3","comment":"甜，水份多","time":"2016-10-09 13:23:14"},
					{"../css/img/personImgurl":"../css/img/person5.jpg","star":"3","comment":"还行。就是价格有点小高。","time":"2016-10-08 12:23:22"},
					{"../css/img/personImgurl":"../css/img/person6.jpg","star":"5","comment":"第二次买了，真心不错","time":"2016-10-07 14:46:12"},
					{"../css/img/personImgurl":"../css/img/person7.jpg","star":"4","comment":"比较酸，皮厚，肉比较硬啊","time":"2016-10-05 15:46:55"},
					{"../css/img/personImgurl":"../css/img/person8.jpg","star":"3","comment":"果果不错，第一次吃很满意","time":"2016-10-04 13:32:16"},
					{"../css/img/personImgurl":"../css/img/person9.jpg","star":"4","comment":"外表看着还行，里面偏干，水分不是很足。","time":"2016-10-01 14:52:52"},
					{"../css/img/personImgurl":"../css/img/person9.jpg","star":"5","comment":"非常好吃 一直都来","time":"2016-09-21 12:32:22"},
					{"../css/img/personImgurl":"../css/img/person11.jpg","star":"3","comment":"水分有点少，甜度有","time":"2016-09-20 08:23:55"},
					{"../css/img/personImgurl":"../css/img/person13.jpg","star":"5","comment":"实体店买了一个红柚有点苦，可是这个柚子就是甜的，而且水分比较足，很赞","time":"2016-09-16 13:32:55"},
					{"../css/img/personImgurl":"../css/img/person14.jpg","star":"3","comment":"不太满意，今年第一次在天天果园买柚子，价格不便宜，但是打开第一个皮厚到飞起，果肉大小跟文旦差不多，也是醉醉的，还是去水果店自己挑比较靠谱","time":"2016-09-14 08:46:21"},
					{"../css/img/personImgurl":"../css/img/person15.jpg","star":"4","comment":"我这次买了4个不怎么样","time":"2016-08-13 12:23:15"},
					{"../css/img/personImgurl":"../css/img/person16.jpg","star":"5","comment":"口感不错。好吃","time":"2016-08-12 18:46:55"},
					{"../css/img/personImgurl":"../css/img/person18.jpg","star":"3","comment":"果皮厚度正常水平，果肉红润，未见\"三红\"，口味上略呈酸味，甜度不高，含水量一般，综上，小贵。","time":"2016-04-06 17:23:51"},
					{"../css/img/personImgurl":"../css/img/person19.jpg","star":"5","comment":"看起来棒棒哒","time":"2016-03-02 02:23:35"},
					{"../css/img/personImgurl":"../css/img/person20.jpg","star":"4","comment":"味道还可以，稍微有些干","time":"2016-02-14 15:46:25"},
					{"../css/img/personImgurl":"../css/img/person21.jpg","star":"4","comment":"这次比上次的好 水分比较多 每一瓣蛮大的 上次的就比较小 就是水分多了不怎么甜","time":"2016-02-10 12:32:55"},
					{"../css/img/personImgurl":"../css/img/person22.jpg","star":"5","comment":"快递小哥很给力","time":"2016-01-12 15:32:45"},
					{"../css/img/personImgurl":"../css/img/person23.jpg","star":"4","comment":"好吃，唯一缺点就是皮太厚咯","time":"2016-01-05 15:23:13"},
					{"../css/img/personImgurl":"../css/img/person24.jpg","star":"3","comment":"很甜，很不错，下次再买！","time":"2016-01-04 12:46:55"},
					{"../css/img/personImgurl":"../css/img/person26.jpg","star":"6","comment":"个头不大，皮超级厚，有点酸，真心不咋地还贵","time":"2015-12-18 08:23:21"},
					{"../css/img/personImgurl":"../css/img/person6.jpg","star":"4","comment":"偏酸喜欢的可以下手了水分很好","time":"2015-10-22 12:32:12"},
					{"../css/img/personImgurl":"../css/img/person27.jpg","star":"4","comment":"不知道这个为什么那么贵，实际就是这样的，皮那么厚，肉也没有那么多汁肥嫩。下次不会买了","time":"2015-07-12 08:32:56"},
					{"../css/img/personImgurl":"../css/img/person28.jpg","star":"4","comment":"起码样子长得挺好看的","time":"2015-07-05 03:12:12"}
				]
	}
	
]